<?xml version='1.0' encoding='UTF-8'?>
<profile>
	<name>CXCommerce_Groovy_2101</name>
	<language>grvy</language>
	<rules>
		<rule>
			<repositoryKey>common-grvy</repositoryKey>
			<key>FailedUnitTests</key>
			<priority>BLOCKER</priority>
			<parameters/>
		</rule>
		<rule>
			<repositoryKey>common-grvy</repositoryKey>
			<key>SkippedUnitTests</key>
			<priority>MAJOR</priority>
			<parameters/>
		</rule>
		<rule>
			<repositoryKey>grvy</repositoryKey>
			<key>org.codenarc.rule.basic.AssignmentInConditionalRule</key>
			<priority>MAJOR</priority>
			<parameters/>
		</rule>
		<rule>
			<repositoryKey>grvy</repositoryKey>
			<key>org.codenarc.rule.basic.BitwiseOperatorInConditionalRule</key>
			<priority>MAJOR</priority>
			<parameters/>
		</rule>
		<rule>
			<repositoryKey>grvy</repositoryKey>
			<key>org.codenarc.rule.basic.BrokenNullCheckRule</key>
			<priority>BLOCKER</priority>
			<parameters/>
		</rule>
		<rule>
			<repositoryKey>grvy</repositoryKey>
			<key>org.codenarc.rule.basic.ComparisonOfTwoConstantsRule</key>
			<priority>MAJOR</priority>
			<parameters/>
		</rule>
		<rule>
			<repositoryKey>grvy</repositoryKey>
			<key>org.codenarc.rule.basic.ComparisonWithSelfRule</key>
			<priority>MAJOR</priority>
			<parameters/>
		</rule>
		<rule>
			<repositoryKey>grvy</repositoryKey>
			<key>org.codenarc.rule.basic.ConstantAssertExpressionRule</key>
			<priority>MAJOR</priority>
			<parameters/>
		</rule>
		<rule>
			<repositoryKey>grvy</repositoryKey>
			<key>org.codenarc.rule.basic.ConstantIfExpressionRule</key>
			<priority>MINOR</priority>
			<parameters/>
		</rule>
		<rule>
			<repositoryKey>grvy</repositoryKey>
			<key>org.codenarc.rule.basic.ConstantTernaryExpressionRule</key>
			<priority>MINOR</priority>
			<parameters/>
		</rule>
		<rule>
			<repositoryKey>grvy</repositoryKey>
			<key>org.codenarc.rule.basic.DeadCodeRule</key>
			<priority>MAJOR</priority>
			<parameters/>
		</rule>
		<rule>
			<repositoryKey>grvy</repositoryKey>
			<key>org.codenarc.rule.basic.DuplicateCaseStatementRule</key>
			<priority>CRITICAL</priority>
			<parameters/>
		</rule>
		<rule>
			<repositoryKey>grvy</repositoryKey>
			<key>org.codenarc.rule.basic.EmptyCatchBlockRule</key>
			<priority>MAJOR</priority>
			<parameters>
				<parameter>
					<key>ignoreRegex</key>
					<value>ignore|ignored</value>
				</parameter>
			</parameters>
		</rule>
		<rule>
			<repositoryKey>grvy</repositoryKey>
			<key>org.codenarc.rule.basic.EmptyClassRule</key>
			<priority>MAJOR</priority>
			<parameters/>
		</rule>
		<rule>
			<repositoryKey>grvy</repositoryKey>
			<key>org.codenarc.rule.basic.EmptyElseBlockRule</key>
			<priority>MAJOR</priority>
			<parameters/>
		</rule>
		<rule>
			<repositoryKey>grvy</repositoryKey>
			<key>org.codenarc.rule.basic.EmptyFinallyBlockRule</key>
			<priority>MAJOR</priority>
			<parameters/>
		</rule>
		<rule>
			<repositoryKey>grvy</repositoryKey>
			<key>org.codenarc.rule.basic.EmptyForStatementRule</key>
			<priority>MAJOR</priority>
			<parameters/>
		</rule>
		<rule>
			<repositoryKey>grvy</repositoryKey>
			<key>org.codenarc.rule.basic.EmptyIfStatementRule</key>
			<priority>INFO</priority>
			<parameters/>
		</rule>
		<rule>
			<repositoryKey>grvy</repositoryKey>
			<key>org.codenarc.rule.basic.EmptyInstanceInitializerRule</key>
			<priority>MAJOR</priority>
			<parameters/>
		</rule>
		<rule>
			<repositoryKey>grvy</repositoryKey>
			<key>org.codenarc.rule.basic.EmptyMethodRule</key>
			<priority>MAJOR</priority>
			<parameters/>
		</rule>
		<rule>
			<repositoryKey>grvy</repositoryKey>
			<key>org.codenarc.rule.basic.EmptyStaticInitializerRule</key>
			<priority>MAJOR</priority>
			<parameters/>
		</rule>
		<rule>
			<repositoryKey>grvy</repositoryKey>
			<key>org.codenarc.rule.basic.EmptySwitchStatementRule</key>
			<priority>MAJOR</priority>
			<parameters/>
		</rule>
		<rule>
			<repositoryKey>grvy</repositoryKey>
			<key>org.codenarc.rule.basic.EmptySynchronizedStatementRule</key>
			<priority>MAJOR</priority>
			<parameters/>
		</rule>
		<rule>
			<repositoryKey>grvy</repositoryKey>
			<key>org.codenarc.rule.basic.EmptyTryBlockRule</key>
			<priority>MAJOR</priority>
			<parameters/>
		</rule>
		<rule>
			<repositoryKey>grvy</repositoryKey>
			<key>org.codenarc.rule.basic.EmptyWhileStatementRule</key>
			<priority>MAJOR</priority>
			<parameters/>
		</rule>
		<rule>
			<repositoryKey>grvy</repositoryKey>
			<key>org.codenarc.rule.basic.ForLoopShouldBeWhileLoopRule</key>
			<priority>MINOR</priority>
			<parameters/>
		</rule>
		<rule>
			<repositoryKey>grvy</repositoryKey>
			<key>org.codenarc.rule.basic.HardCodedWindowsFileSeparatorRule</key>
			<priority>MINOR</priority>
			<parameters/>
		</rule>
		<rule>
			<repositoryKey>grvy</repositoryKey>
			<key>org.codenarc.rule.basic.HardCodedWindowsRootDirectoryRule</key>
			<priority>CRITICAL</priority>
			<parameters/>
		</rule>
		<rule>
			<repositoryKey>grvy</repositoryKey>
			<key>org.codenarc.rule.basic.RandomDoubleCoercedToZeroRule</key>
			<priority>MAJOR</priority>
			<parameters/>
		</rule>
		<rule>
			<repositoryKey>grvy</repositoryKey>
			<key>org.codenarc.rule.basic.RemoveAllOnSelfRule</key>
			<priority>MINOR</priority>
			<parameters/>
		</rule>
		<rule>
			<repositoryKey>grvy</repositoryKey>
			<key>org.codenarc.rule.braces.ElseBlockBracesRule</key>
			<priority>MINOR</priority>
			<parameters>
				<parameter>
					<key>bracesRequiredForElseIf</key>
					<value>false</value>
				</parameter>
			</parameters>
		</rule>
		<rule>
			<repositoryKey>grvy</repositoryKey>
			<key>org.codenarc.rule.braces.ForStatementBracesRule</key>
			<priority>MINOR</priority>
			<parameters/>
		</rule>
		<rule>
			<repositoryKey>grvy</repositoryKey>
			<key>org.codenarc.rule.braces.IfStatementBracesRule</key>
			<priority>MINOR</priority>
			<parameters/>
		</rule>
		<rule>
			<repositoryKey>grvy</repositoryKey>
			<key>org.codenarc.rule.braces.WhileStatementBracesRule</key>
			<priority>MINOR</priority>
			<parameters/>
		</rule>
		<rule>
			<repositoryKey>grvy</repositoryKey>
			<key>org.codenarc.rule.comments.JavadocConsecutiveEmptyLinesRule</key>
			<priority>MINOR</priority>
			<parameters/>
		</rule>
		<rule>
			<repositoryKey>grvy</repositoryKey>
			<key>org.codenarc.rule.comments.JavadocEmptyAuthorTagRule</key>
			<priority>MAJOR</priority>
			<parameters>
				<parameter>
					<key>allowMultiline</key>
					<value>false</value>
				</parameter>
			</parameters>
		</rule>
		<rule>
			<repositoryKey>grvy</repositoryKey>
			<key>org.codenarc.rule.comments.JavadocEmptyExceptionTagRule</key>
			<priority>MAJOR</priority>
			<parameters>
				<parameter>
					<key>allowMultiline</key>
					<value>false</value>
				</parameter>
			</parameters>
		</rule>
		<rule>
			<repositoryKey>grvy</repositoryKey>
			<key>org.codenarc.rule.comments.JavadocEmptyFirstLineRule</key>
			<priority>MINOR</priority>
			<parameters/>
		</rule>
		<rule>
			<repositoryKey>grvy</repositoryKey>
			<key>org.codenarc.rule.comments.JavadocEmptyLastLineRule</key>
			<priority>MINOR</priority>
			<parameters/>
		</rule>
		<rule>
			<repositoryKey>grvy</repositoryKey>
			<key>org.codenarc.rule.comments.JavadocEmptyParamTagRule</key>
			<priority>MAJOR</priority>
			<parameters>
				<parameter>
					<key>allowMultiline</key>
					<value>false</value>
				</parameter>
			</parameters>
		</rule>
		<rule>
			<repositoryKey>grvy</repositoryKey>
			<key>org.codenarc.rule.comments.JavadocEmptyReturnTagRule</key>
			<priority>MAJOR</priority>
			<parameters>
				<parameter>
					<key>allowMultiline</key>
					<value>false</value>
				</parameter>
			</parameters>
		</rule>
		<rule>
			<repositoryKey>grvy</repositoryKey>
			<key>org.codenarc.rule.comments.JavadocEmptySeeTagRule</key>
			<priority>MAJOR</priority>
			<parameters>
				<parameter>
					<key>allowMultiline</key>
					<value>false</value>
				</parameter>
			</parameters>
		</rule>
		<rule>
			<repositoryKey>grvy</repositoryKey>
			<key>org.codenarc.rule.comments.JavadocEmptySinceTagRule</key>
			<priority>MAJOR</priority>
			<parameters>
				<parameter>
					<key>allowMultiline</key>
					<value>false</value>
				</parameter>
			</parameters>
		</rule>
		<rule>
			<repositoryKey>grvy</repositoryKey>
			<key>org.codenarc.rule.comments.JavadocEmptyThrowsTagRule</key>
			<priority>MAJOR</priority>
			<parameters>
				<parameter>
					<key>allowMultiline</key>
					<value>false</value>
				</parameter>
			</parameters>
		</rule>
		<rule>
			<repositoryKey>grvy</repositoryKey>
			<key>org.codenarc.rule.comments.JavadocEmptyVersionTagRule</key>
			<priority>MAJOR</priority>
			<parameters>
				<parameter>
					<key>allowMultiline</key>
					<value>false</value>
				</parameter>
			</parameters>
		</rule>
		<rule>
			<repositoryKey>grvy</repositoryKey>
			<key>org.codenarc.rule.comments.JavadocMissingExceptionDescriptionRule</key>
			<priority>MAJOR</priority>
			<parameters>
				<parameter>
					<key>allowMultiline</key>
					<value>false</value>
				</parameter>
			</parameters>
		</rule>
		<rule>
			<repositoryKey>grvy</repositoryKey>
			<key>org.codenarc.rule.comments.JavadocMissingParamDescriptionRule</key>
			<priority>MAJOR</priority>
			<parameters>
				<parameter>
					<key>allowMultiline</key>
					<value>true</value>
				</parameter>
			</parameters>
		</rule>
		<rule>
			<repositoryKey>grvy</repositoryKey>
			<key>org.codenarc.rule.comments.JavadocMissingThrowsDescriptionRule</key>
			<priority>MAJOR</priority>
			<parameters>
				<parameter>
					<key>allowMultiline</key>
					<value>false</value>
				</parameter>
			</parameters>
		</rule>
		<rule>
			<repositoryKey>grvy</repositoryKey>
			<key>org.codenarc.rule.convention.ConfusingTernaryRule</key>
			<priority>MAJOR</priority>
			<parameters/>
		</rule>
		<rule>
			<repositoryKey>grvy</repositoryKey>
			<key>org.codenarc.rule.convention.CouldBeElvisRule</key>
			<priority>INFO</priority>
			<parameters/>
		</rule>
		<rule>
			<repositoryKey>grvy</repositoryKey>
			<key>org.codenarc.rule.convention.CouldBeSwitchStatementRule</key>
			<priority>MINOR</priority>
			<parameters/>
		</rule>
		<rule>
			<repositoryKey>grvy</repositoryKey>
			<key>org.codenarc.rule.convention.HashtableIsObsoleteRule</key>
			<priority>MAJOR</priority>
			<parameters/>
		</rule>
		<rule>
			<repositoryKey>grvy</repositoryKey>
			<key>org.codenarc.rule.convention.InvertedConditionRule</key>
			<priority>MINOR</priority>
			<parameters/>
		</rule>
		<rule>
			<repositoryKey>grvy</repositoryKey>
			<key>org.codenarc.rule.convention.InvertedIfElseRule</key>
			<priority>MAJOR</priority>
			<parameters/>
		</rule>
		<rule>
			<repositoryKey>grvy</repositoryKey>
			<key>org.codenarc.rule.convention.ParameterReassignmentRule</key>
			<priority>MAJOR</priority>
			<parameters/>
		</rule>
		<rule>
			<repositoryKey>grvy</repositoryKey>
			<key>org.codenarc.rule.convention.StaticFieldsBeforeInstanceFieldsRule</key>
			<priority>MINOR</priority>
			<parameters/>
		</rule>
		<rule>
			<repositoryKey>grvy</repositoryKey>
			<key>org.codenarc.rule.convention.TernaryCouldBeElvisRule</key>
			<priority>MINOR</priority>
			<parameters/>
		</rule>
		<rule>
			<repositoryKey>grvy</repositoryKey>
			<key>org.codenarc.rule.convention.VectorIsObsoleteRule</key>
			<priority>MAJOR</priority>
			<parameters/>
		</rule>
		<rule>
			<repositoryKey>grvy</repositoryKey>
			<key>org.codenarc.rule.design.PrivateFieldCouldBeFinalRule.fixed</key>
			<priority>INFO</priority>
			<parameters>
				<parameter>
					<key>ignoreJpaEntities</key>
					<value>false</value>
				</parameter>
			</parameters>
		</rule>
		<rule>
			<repositoryKey>grvy</repositoryKey>
			<key>org.codenarc.rule.enhanced.MissingOverrideAnnotationRule</key>
			<priority>MAJOR</priority>
			<parameters/>
		</rule>
		<rule>
			<repositoryKey>grvy</repositoryKey>
			<key>org.codenarc.rule.exceptions.CatchArrayIndexOutOfBoundsExceptionRule</key>
			<priority>MAJOR</priority>
			<parameters/>
		</rule>
		<rule>
			<repositoryKey>grvy</repositoryKey>
			<key>org.codenarc.rule.exceptions.CatchErrorRule</key>
			<priority>MAJOR</priority>
			<parameters/>
		</rule>
		<rule>
			<repositoryKey>grvy</repositoryKey>
			<key>org.codenarc.rule.exceptions.CatchIllegalMonitorStateExceptionRule</key>
			<priority>MAJOR</priority>
			<parameters/>
		</rule>
		<rule>
			<repositoryKey>grvy</repositoryKey>
			<key>org.codenarc.rule.exceptions.CatchIndexOutOfBoundsExceptionRule</key>
			<priority>MAJOR</priority>
			<parameters/>
		</rule>
		<rule>
			<repositoryKey>grvy</repositoryKey>
			<key>org.codenarc.rule.exceptions.CatchNullPointerExceptionRule</key>
			<priority>MAJOR</priority>
			<parameters/>
		</rule>
		<rule>
			<repositoryKey>grvy</repositoryKey>
			<key>org.codenarc.rule.exceptions.CatchRuntimeExceptionRule</key>
			<priority>MAJOR</priority>
			<parameters/>
		</rule>
		<rule>
			<repositoryKey>grvy</repositoryKey>
			<key>org.codenarc.rule.exceptions.CatchThrowableRule</key>
			<priority>MAJOR</priority>
			<parameters/>
		</rule>
		<rule>
			<repositoryKey>grvy</repositoryKey>
			<key>org.codenarc.rule.formatting.BlankLineBeforePackageRule</key>
			<priority>INFO</priority>
			<parameters/>
		</rule>
		<rule>
			<repositoryKey>grvy</repositoryKey>
			<key>org.codenarc.rule.formatting.ClosureStatementOnOpeningLineOfMultipleLineClosureRule</key>
			<priority>INFO</priority>
			<parameters/>
		</rule>
		<rule>
			<repositoryKey>grvy</repositoryKey>
			<key>org.codenarc.rule.formatting.ConsecutiveBlankLinesRule</key>
			<priority>INFO</priority>
			<parameters/>
		</rule>
		<rule>
			<repositoryKey>grvy</repositoryKey>
			<key>org.codenarc.rule.formatting.FileEndsWithoutNewlineRule</key>
			<priority>MAJOR</priority>
			<parameters/>
		</rule>
		<rule>
			<repositoryKey>grvy</repositoryKey>
			<key>org.codenarc.rule.formatting.MissingBlankLineAfterImportsRule</key>
			<priority>INFO</priority>
			<parameters/>
		</rule>
		<rule>
			<repositoryKey>grvy</repositoryKey>
			<key>org.codenarc.rule.formatting.MissingBlankLineAfterPackageRule</key>
			<priority>INFO</priority>
			<parameters/>
		</rule>
		<rule>
			<repositoryKey>grvy</repositoryKey>
			<key>org.codenarc.rule.formatting.SpaceAfterCatchRule</key>
			<priority>INFO</priority>
			<parameters/>
		</rule>
		<rule>
			<repositoryKey>grvy</repositoryKey>
			<key>org.codenarc.rule.formatting.SpaceAfterClosingBraceRule</key>
			<priority>INFO</priority>
			<parameters>
				<parameter>
					<key>checkClosureMapEntryValue</key>
					<value>true</value>
				</parameter>
			</parameters>
		</rule>
		<rule>
			<repositoryKey>grvy</repositoryKey>
			<key>org.codenarc.rule.formatting.SpaceAfterCommaRule</key>
			<priority>INFO</priority>
			<parameters/>
		</rule>
		<rule>
			<repositoryKey>grvy</repositoryKey>
			<key>org.codenarc.rule.formatting.SpaceAfterForRule</key>
			<priority>INFO</priority>
			<parameters/>
		</rule>
		<rule>
			<repositoryKey>grvy</repositoryKey>
			<key>org.codenarc.rule.formatting.SpaceAfterIfRule</key>
			<priority>INFO</priority>
			<parameters/>
		</rule>
		<rule>
			<repositoryKey>grvy</repositoryKey>
			<key>org.codenarc.rule.formatting.SpaceAfterOpeningBraceRule</key>
			<priority>INFO</priority>
			<parameters>
				<parameter>
					<key>ignoreEmptyBlock</key>
					<value>true</value>
				</parameter>
				<parameter>
					<key>checkClosureMapEntryValue</key>
					<value>true</value>
				</parameter>
			</parameters>
		</rule>
		<rule>
			<repositoryKey>grvy</repositoryKey>
			<key>org.codenarc.rule.formatting.SpaceAfterSemicolonRule</key>
			<priority>INFO</priority>
			<parameters/>
		</rule>
		<rule>
			<repositoryKey>grvy</repositoryKey>
			<key>org.codenarc.rule.formatting.SpaceAfterSwitchRule</key>
			<priority>INFO</priority>
			<parameters/>
		</rule>
		<rule>
			<repositoryKey>grvy</repositoryKey>
			<key>org.codenarc.rule.formatting.SpaceAfterWhileRule</key>
			<priority>INFO</priority>
			<parameters/>
		</rule>
		<rule>
			<repositoryKey>grvy</repositoryKey>
			<key>org.codenarc.rule.formatting.SpaceAroundClosureArrowRule</key>
			<priority>INFO</priority>
			<parameters/>
		</rule>
		<rule>
			<repositoryKey>grvy</repositoryKey>
			<key>org.codenarc.rule.formatting.SpaceAroundOperatorRule</key>
			<priority>INFO</priority>
			<parameters>
				<parameter>
					<key>ignoreParameterDefaultValueAssignments</key>
					<value>false</value>
				</parameter>
			</parameters>
		</rule>
		<rule>
			<repositoryKey>grvy</repositoryKey>
			<key>org.codenarc.rule.formatting.SpaceBeforeClosingBraceRule</key>
			<priority>INFO</priority>
			<parameters>
				<parameter>
					<key>ignoreEmptyBlock</key>
					<value>true</value>
				</parameter>
				<parameter>
					<key>checkClosureMapEntryValue</key>
					<value>true</value>
				</parameter>
			</parameters>
		</rule>
		<rule>
			<repositoryKey>grvy</repositoryKey>
			<key>org.codenarc.rule.formatting.SpaceBeforeOpeningBraceRule</key>
			<priority>INFO</priority>
			<parameters>
				<parameter>
					<key>checkClosureMapEntryValue</key>
					<value>true</value>
				</parameter>
			</parameters>
		</rule>
		<rule>
			<repositoryKey>grvy</repositoryKey>
			<key>org.codenarc.rule.formatting.TrailingWhitespaceRule</key>
			<priority>INFO</priority>
			<parameters/>
		</rule>
		<rule>
			<repositoryKey>grvy</repositoryKey>
			<key>org.codenarc.rule.groovyism.AssignCollectionSortRule</key>
			<priority>MAJOR</priority>
			<parameters/>
		</rule>
		<rule>
			<repositoryKey>grvy</repositoryKey>
			<key>org.codenarc.rule.groovyism.AssignCollectionUniqueRule</key>
			<priority>MAJOR</priority>
			<parameters/>
		</rule>
		<rule>
			<repositoryKey>grvy</repositoryKey>
			<key>org.codenarc.rule.groovyism.CollectAllIsDeprecatedRule</key>
			<priority>MINOR</priority>
			<parameters/>
		</rule>
		<rule>
			<repositoryKey>grvy</repositoryKey>
			<key>org.codenarc.rule.groovyism.GroovyLangImmutableRule</key>
			<priority>MINOR</priority>
			<parameters/>
		</rule>
		<rule>
			<repositoryKey>grvy</repositoryKey>
			<key>org.codenarc.rule.imports.DuplicateImportRule</key>
			<priority>MAJOR</priority>
			<parameters/>
		</rule>
		<rule>
			<repositoryKey>grvy</repositoryKey>
			<key>org.codenarc.rule.imports.ImportFromSamePackageRule</key>
			<priority>MAJOR</priority>
			<parameters/>
		</rule>
		<rule>
			<repositoryKey>grvy</repositoryKey>
			<key>org.codenarc.rule.imports.ImportFromSunPackagesRule</key>
			<priority>BLOCKER</priority>
			<parameters/>
		</rule>
		<rule>
			<repositoryKey>grvy</repositoryKey>
			<key>org.codenarc.rule.imports.MisorderedStaticImportsRule</key>
			<priority>MINOR</priority>
			<parameters>
				<parameter>
					<key>comesBefore</key>
					<value>true</value>
				</parameter>
			</parameters>
		</rule>
		<rule>
			<repositoryKey>grvy</repositoryKey>
			<key>org.codenarc.rule.imports.NoWildcardImportsRule</key>
			<priority>MAJOR</priority>
			<parameters>
				<parameter>
					<key>ignoreImports</key>
					<value>false</value>
				</parameter>
				<parameter>
					<key>ignoreStaticImports</key>
					<value>false</value>
				</parameter>
			</parameters>
		</rule>
		<rule>
			<repositoryKey>grvy</repositoryKey>
			<key>org.codenarc.rule.imports.UnnecessaryGroovyImportRule</key>
			<priority>MAJOR</priority>
			<parameters/>
		</rule>
		<rule>
			<repositoryKey>grvy</repositoryKey>
			<key>org.codenarc.rule.imports.UnusedImportRule</key>
			<priority>MAJOR</priority>
			<parameters/>
		</rule>
		<rule>
			<repositoryKey>grvy</repositoryKey>
			<key>org.codenarc.rule.junit.JUnitPublicFieldRule</key>
			<priority>MINOR</priority>
			<parameters/>
		</rule>
		<rule>
			<repositoryKey>grvy</repositoryKey>
			<key>org.codenarc.rule.junit.JUnitUnnecessarySetUpRule</key>
			<priority>MINOR</priority>
			<parameters/>
		</rule>
		<rule>
			<repositoryKey>grvy</repositoryKey>
			<key>org.codenarc.rule.junit.JUnitUnnecessaryTearDownRule</key>
			<priority>MINOR</priority>
			<parameters/>
		</rule>
		<rule>
			<repositoryKey>grvy</repositoryKey>
			<key>org.codenarc.rule.junit.JUnitUnnecessaryThrowsExceptionRule</key>
			<priority>MINOR</priority>
			<parameters/>
		</rule>
		<rule>
			<repositoryKey>grvy</repositoryKey>
			<key>org.codenarc.rule.junit.UseAssertEqualsInsteadOfAssertTrueRule</key>
			<priority>MINOR</priority>
			<parameters/>
		</rule>
		<rule>
			<repositoryKey>grvy</repositoryKey>
			<key>org.codenarc.rule.junit.UseAssertNullInsteadOfAssertEqualsRule</key>
			<priority>MINOR</priority>
			<parameters/>
		</rule>
		<rule>
			<repositoryKey>grvy</repositoryKey>
			<key>org.codenarc.rule.junit.UseAssertSameInsteadOfAssertTrueRule</key>
			<priority>MINOR</priority>
			<parameters/>
		</rule>
		<rule>
			<repositoryKey>grvy</repositoryKey>
			<key>org.codenarc.rule.junit.UseAssertTrueInsteadOfAssertEqualsRule</key>
			<priority>MINOR</priority>
			<parameters>
				<parameter>
					<key>checkAssertStatements</key>
					<value>true</value>
				</parameter>
			</parameters>
		</rule>
		<rule>
			<repositoryKey>grvy</repositoryKey>
			<key>org.codenarc.rule.naming.ClassNameRule</key>
			<priority>MAJOR</priority>
			<parameters>
				<parameter>
					<key>regex</key>
					<value>([A-Z]\w*\$?)+</value>
				</parameter>
			</parameters>
		</rule>
		<rule>
			<repositoryKey>grvy</repositoryKey>
			<key>org.codenarc.rule.naming.ClassNameSameAsFilenameRule</key>
			<priority>MAJOR</priority>
			<parameters/>
		</rule>
		<rule>
			<repositoryKey>grvy</repositoryKey>
			<key>org.codenarc.rule.naming.ClassNameSameAsSuperclassRule</key>
			<priority>MAJOR</priority>
			<parameters/>
		</rule>
		<rule>
			<repositoryKey>grvy</repositoryKey>
			<key>org.codenarc.rule.naming.ObjectOverrideMisspelledMethodNameRule</key>
			<priority>MAJOR</priority>
			<parameters/>
		</rule>
		<rule>
			<repositoryKey>grvy</repositoryKey>
			<key>org.codenarc.rule.security.InsecureRandomRule</key>
			<priority>INFO</priority>
			<parameters/>
		</rule>
		<rule>
			<repositoryKey>grvy</repositoryKey>
			<key>org.codenarc.rule.security.ObjectFinalizeRule</key>
			<priority>MINOR</priority>
			<parameters/>
		</rule>
		<rule>
			<repositoryKey>grvy</repositoryKey>
			<key>org.codenarc.rule.security.PublicFinalizeMethodRule</key>
			<priority>MINOR</priority>
			<parameters/>
		</rule>
		<rule>
			<repositoryKey>grvy</repositoryKey>
			<key>org.codenarc.rule.security.UnsafeArrayDeclarationRule</key>
			<priority>MINOR</priority>
			<parameters/>
		</rule>
		<rule>
			<repositoryKey>grvy</repositoryKey>
			<key>org.codenarc.rule.security.UnsafeImplementationAsMapRule</key>
			<priority>MAJOR</priority>
			<parameters/>
		</rule>
		<rule>
			<repositoryKey>grvy</repositoryKey>
			<key>org.codenarc.rule.serialization.EnumCustomSerializationIgnoredRule</key>
			<priority>MAJOR</priority>
			<parameters/>
		</rule>
		<rule>
			<repositoryKey>grvy</repositoryKey>
			<key>org.codenarc.rule.serialization.SerialPersistentFieldsRule</key>
			<priority>MAJOR</priority>
			<parameters/>
		</rule>
		<rule>
			<repositoryKey>grvy</repositoryKey>
			<key>org.codenarc.rule.serialization.SerialVersionUIDRule</key>
			<priority>MAJOR</priority>
			<parameters/>
		</rule>
		<rule>
			<repositoryKey>grvy</repositoryKey>
			<key>org.codenarc.rule.size.ClassSizeRule</key>
			<priority>MAJOR</priority>
			<parameters>
				<parameter>
					<key>maxLines</key>
					<value>1000</value>
				</parameter>
			</parameters>
		</rule>
		<rule>
			<repositoryKey>grvy</repositoryKey>
			<key>org.codenarc.rule.size.MethodSizeRule.fixed</key>
			<priority>MAJOR</priority>
			<parameters>
				<parameter>
					<key>maxLines</key>
					<value>100</value>
				</parameter>
			</parameters>
		</rule>
		<rule>
			<repositoryKey>grvy</repositoryKey>
			<key>org.codenarc.rule.unnecessary.AddEmptyStringRule</key>
			<priority>MINOR</priority>
			<parameters/>
		</rule>
		<rule>
			<repositoryKey>grvy</repositoryKey>
			<key>org.codenarc.rule.unnecessary.ConsecutiveLiteralAppendsRule</key>
			<priority>INFO</priority>
			<parameters/>
		</rule>
		<rule>
			<repositoryKey>grvy</repositoryKey>
			<key>org.codenarc.rule.unnecessary.ConsecutiveStringConcatenationRule</key>
			<priority>MAJOR</priority>
			<parameters/>
		</rule>
		<rule>
			<repositoryKey>grvy</repositoryKey>
			<key>org.codenarc.rule.unnecessary.UnnecessaryBigDecimalInstantiationRule</key>
			<priority>MAJOR</priority>
			<parameters/>
		</rule>
		<rule>
			<repositoryKey>grvy</repositoryKey>
			<key>org.codenarc.rule.unnecessary.UnnecessaryBigIntegerInstantiationRule</key>
			<priority>MAJOR</priority>
			<parameters/>
		</rule>
		<rule>
			<repositoryKey>grvy</repositoryKey>
			<key>org.codenarc.rule.unnecessary.UnnecessaryBooleanExpressionRule</key>
			<priority>MAJOR</priority>
			<parameters/>
		</rule>
		<rule>
			<repositoryKey>grvy</repositoryKey>
			<key>org.codenarc.rule.unnecessary.UnnecessaryBooleanInstantiationRule</key>
			<priority>MAJOR</priority>
			<parameters/>
		</rule>
		<rule>
			<repositoryKey>grvy</repositoryKey>
			<key>org.codenarc.rule.unnecessary.UnnecessaryCallForLastElementRule</key>
			<priority>MAJOR</priority>
			<parameters/>
		</rule>
		<rule>
			<repositoryKey>grvy</repositoryKey>
			<key>org.codenarc.rule.unnecessary.UnnecessaryCallToSubstringRule</key>
			<priority>MINOR</priority>
			<parameters/>
		</rule>
		<rule>
			<repositoryKey>grvy</repositoryKey>
			<key>org.codenarc.rule.unnecessary.UnnecessaryCatchBlockRule</key>
			<priority>MINOR</priority>
			<parameters/>
		</rule>
		<rule>
			<repositoryKey>grvy</repositoryKey>
			<key>org.codenarc.rule.unnecessary.UnnecessaryCollectCallRule</key>
			<priority>MINOR</priority>
			<parameters/>
		</rule>
		<rule>
			<repositoryKey>grvy</repositoryKey>
			<key>org.codenarc.rule.unnecessary.UnnecessaryCollectionCallRule</key>
			<priority>MINOR</priority>
			<parameters/>
		</rule>
		<rule>
			<repositoryKey>grvy</repositoryKey>
			<key>org.codenarc.rule.unnecessary.UnnecessaryConstructorRule</key>
			<priority>MINOR</priority>
			<parameters>
				<parameter>
					<key>ignoreAnnotations</key>
					<value>false</value>
				</parameter>
			</parameters>
		</rule>
		<rule>
			<repositoryKey>grvy</repositoryKey>
			<key>org.codenarc.rule.unnecessary.UnnecessaryDefInFieldDeclarationRule</key>
			<priority>MINOR</priority>
			<parameters/>
		</rule>
		<rule>
			<repositoryKey>grvy</repositoryKey>
			<key>org.codenarc.rule.unnecessary.UnnecessaryDefInMethodDeclarationRule</key>
			<priority>MINOR</priority>
			<parameters/>
		</rule>
		<rule>
			<repositoryKey>grvy</repositoryKey>
			<key>org.codenarc.rule.unnecessary.UnnecessaryDefInVariableDeclarationRule</key>
			<priority>MINOR</priority>
			<parameters/>
		</rule>
		<rule>
			<repositoryKey>grvy</repositoryKey>
			<key>org.codenarc.rule.unnecessary.UnnecessaryDotClassRule</key>
			<priority>MINOR</priority>
			<parameters/>
		</rule>
		<rule>
			<repositoryKey>grvy</repositoryKey>
			<key>org.codenarc.rule.unnecessary.UnnecessaryDoubleInstantiationRule</key>
			<priority>MAJOR</priority>
			<parameters/>
		</rule>
		<rule>
			<repositoryKey>grvy</repositoryKey>
			<key>org.codenarc.rule.unnecessary.UnnecessaryElseStatementRule</key>
			<priority>MINOR</priority>
			<parameters/>
		</rule>
		<rule>
			<repositoryKey>grvy</repositoryKey>
			<key>org.codenarc.rule.unnecessary.UnnecessaryFinalOnPrivateMethodRule</key>
			<priority>MINOR</priority>
			<parameters/>
		</rule>
		<rule>
			<repositoryKey>grvy</repositoryKey>
			<key>org.codenarc.rule.unnecessary.UnnecessaryFloatInstantiationRule</key>
			<priority>MAJOR</priority>
			<parameters/>
		</rule>
		<rule>
			<repositoryKey>grvy</repositoryKey>
			<key>org.codenarc.rule.unnecessary.UnnecessaryGStringRule</key>
			<priority>MINOR</priority>
			<parameters/>
		</rule>
		<rule>
			<repositoryKey>grvy</repositoryKey>
			<key>org.codenarc.rule.unnecessary.UnnecessaryGetterRule</key>
			<priority>INFO</priority>
			<parameters>
				<parameter>
					<key>checkIsMethods</key>
					<value>true</value>
				</parameter>
			</parameters>
		</rule>
		<rule>
			<repositoryKey>grvy</repositoryKey>
			<key>org.codenarc.rule.unnecessary.UnnecessaryIfStatementRule</key>
			<priority>MINOR</priority>
			<parameters/>
		</rule>
		<rule>
			<repositoryKey>grvy</repositoryKey>
			<key>org.codenarc.rule.unnecessary.UnnecessaryInstanceOfCheckRule</key>
			<priority>MINOR</priority>
			<parameters/>
		</rule>
		<rule>
			<repositoryKey>grvy</repositoryKey>
			<key>org.codenarc.rule.unnecessary.UnnecessaryInstantiationToGetClassRule</key>
			<priority>MAJOR</priority>
			<parameters/>
		</rule>
		<rule>
			<repositoryKey>grvy</repositoryKey>
			<key>org.codenarc.rule.unnecessary.UnnecessaryIntegerInstantiationRule</key>
			<priority>MAJOR</priority>
			<parameters/>
		</rule>
		<rule>
			<repositoryKey>grvy</repositoryKey>
			<key>org.codenarc.rule.unnecessary.UnnecessaryLongInstantiationRule</key>
			<priority>MAJOR</priority>
			<parameters/>
		</rule>
		<rule>
			<repositoryKey>grvy</repositoryKey>
			<key>org.codenarc.rule.unnecessary.UnnecessaryModOneRule</key>
			<priority>MAJOR</priority>
			<parameters/>
		</rule>
		<rule>
			<repositoryKey>grvy</repositoryKey>
			<key>org.codenarc.rule.unnecessary.UnnecessaryNullCheckBeforeInstanceOfRule</key>
			<priority>MAJOR</priority>
			<parameters/>
		</rule>
		<rule>
			<repositoryKey>grvy</repositoryKey>
			<key>org.codenarc.rule.unnecessary.UnnecessaryNullCheckRule</key>
			<priority>MAJOR</priority>
			<parameters/>
		</rule>
		<rule>
			<repositoryKey>grvy</repositoryKey>
			<key>org.codenarc.rule.unnecessary.UnnecessaryObjectReferencesRule</key>
			<priority>INFO</priority>
			<parameters/>
		</rule>
		<rule>
			<repositoryKey>grvy</repositoryKey>
			<key>org.codenarc.rule.unnecessary.UnnecessaryOverridingMethodRule</key>
			<priority>MINOR</priority>
			<parameters/>
		</rule>
		<rule>
			<repositoryKey>grvy</repositoryKey>
			<key>org.codenarc.rule.unnecessary.UnnecessaryPackageReferenceRule</key>
			<priority>MINOR</priority>
			<parameters/>
		</rule>
		<rule>
			<repositoryKey>grvy</repositoryKey>
			<key>org.codenarc.rule.unnecessary.UnnecessaryParenthesesForMethodCallWithClosureRule</key>
			<priority>MINOR</priority>
			<parameters/>
		</rule>
		<rule>
			<repositoryKey>grvy</repositoryKey>
			<key>org.codenarc.rule.unnecessary.UnnecessaryPublicModifierRule</key>
			<priority>MINOR</priority>
			<parameters/>
		</rule>
		<rule>
			<repositoryKey>grvy</repositoryKey>
			<key>org.codenarc.rule.unnecessary.UnnecessarySafeNavigationOperatorRule</key>
			<priority>MAJOR</priority>
			<parameters/>
		</rule>
		<rule>
			<repositoryKey>grvy</repositoryKey>
			<key>org.codenarc.rule.unnecessary.UnnecessarySelfAssignmentRule</key>
			<priority>MAJOR</priority>
			<parameters/>
		</rule>
		<rule>
			<repositoryKey>grvy</repositoryKey>
			<key>org.codenarc.rule.unnecessary.UnnecessarySemicolonRule</key>
			<priority>MINOR</priority>
			<parameters/>
		</rule>
		<rule>
			<repositoryKey>grvy</repositoryKey>
			<key>org.codenarc.rule.unnecessary.UnnecessarySetterRule</key>
			<priority>INFO</priority>
			<parameters/>
		</rule>
		<rule>
			<repositoryKey>grvy</repositoryKey>
			<key>org.codenarc.rule.unnecessary.UnnecessaryStringInstantiationRule</key>
			<priority>MAJOR</priority>
			<parameters/>
		</rule>
		<rule>
			<repositoryKey>grvy</repositoryKey>
			<key>org.codenarc.rule.unnecessary.UnnecessarySubstringRule</key>
			<priority>INFO</priority>
			<parameters/>
		</rule>
		<rule>
			<repositoryKey>grvy</repositoryKey>
			<key>org.codenarc.rule.unnecessary.UnnecessaryTernaryExpressionRule</key>
			<priority>MAJOR</priority>
			<parameters/>
		</rule>
		<rule>
			<repositoryKey>grvy</repositoryKey>
			<key>org.codenarc.rule.unnecessary.UnnecessaryTransientModifierRule</key>
			<priority>MINOR</priority>
			<parameters/>
		</rule>
		<rule>
			<repositoryKey>grvy</repositoryKey>
			<key>org.codenarc.rule.unused.UnusedArrayRule</key>
			<priority>MAJOR</priority>
			<parameters/>
		</rule>
		<rule>
			<repositoryKey>grvy</repositoryKey>
			<key>org.codenarc.rule.unused.UnusedMethodParameterRule</key>
			<priority>MAJOR</priority>
			<parameters>
				<parameter>
					<key>ignoreRegex</key>
					<value>^(ignore|ignored)[0-9]*$</value>
				</parameter>
				<parameter>
					<key>ignoreClassRegex</key>
					<value>.*Category</value>
				</parameter>
			</parameters>
		</rule>
		<rule>
			<repositoryKey>grvy</repositoryKey>
			<key>org.codenarc.rule.unused.UnusedObjectRule</key>
			<priority>MAJOR</priority>
			<parameters/>
		</rule>
		<rule>
			<repositoryKey>grvy</repositoryKey>
			<key>org.codenarc.rule.unused.UnusedPrivateFieldRule</key>
			<priority>MAJOR</priority>
			<parameters>
				<parameter>
					<key>ignoreFieldNames</key>
					<value>serialVersionUID</value>
				</parameter>
			</parameters>
		</rule>
		<rule>
			<repositoryKey>grvy</repositoryKey>
			<key>org.codenarc.rule.unused.UnusedPrivateMethodParameterRule</key>
			<priority>MAJOR</priority>
			<parameters/>
		</rule>
		<rule>
			<repositoryKey>grvy</repositoryKey>
			<key>org.codenarc.rule.unused.UnusedPrivateMethodRule</key>
			<priority>MAJOR</priority>
			<parameters/>
		</rule>
		<rule>
			<repositoryKey>grvy</repositoryKey>
			<key>org.codenarc.rule.unused.UnusedVariableRule.fixed</key>
			<priority>MAJOR</priority>
			<parameters/>
		</rule>
	</rules>
</profile>
